pyweatherflowudp/__init__.py
pyweatherflowudp/aioudp.py
pyweatherflowudp/calc.py
pyweatherflowudp/client.py
pyweatherflowudp/const.py
pyweatherflowudp/device.py
pyweatherflowudp/enums.py
pyweatherflowudp/errors.py
pyweatherflowudp/event.py
pyweatherflowudp/helpers.py
pyweatherflowudp/mixins.py
pyweatherflowudp-1.4.5.dist-info/LICENSE
pyweatherflowudp-1.4.5.dist-info/METADATA
pyweatherflowudp-1.4.5.dist-info/WHEEL
pyweatherflowudp-1.4.5.dist-info/RECORD
