Metadata-Version: 2.1
Name: pyweatherflowudp
Version: 1.4.5
Summary: An event-based asynchronous library to read UDP packets from Weatherflow weather systems on a local network without any reliance on the cloud.
Home-page: https://github.com/briis/pyweatherflowudp
License: MIT
Keywords: WeatherFlow,UDP,asynchronous,local
Author: Nathan Spencer
Author-email: natekspencer@gmail.com
Requires-Python: >=3.8,<4.0
Classifier: License :: OSI Approved :: MIT License
Classifier: Programming Language :: Python :: 3
Classifier: Programming Language :: Python :: 3.8
Classifier: Programming Language :: Python :: 3.9
Classifier: Programming Language :: Python :: 3.10
Classifier: Programming Language :: Python :: 3.11
Requires-Dist: Pint (>=0.19)
Requires-Dist: PsychroLib (>=2.5.0,<3.0.0)
Project-URL: Repository, https://github.com/briis/pyweatherflowudp
